{
  "list": [
    {
      "id": 11022,
      "appearance": "11003_Sinclair_ZweiAppearance",
      "unitKeywordList": [
        "FIXER",
        "SMALL"
      ],
      "associationList": [
        "ZWEI"
      ],
      "characterId": 10,
      "panicType": 9999,
      "season": 0,
      "defenseSkillIDList": [
        1100304
      ],
      "panicSkillOnErosion": 1000104,
      "slotWeightConditionList": [
        "Default1"
      ],
      "rank": 2,
      "hp": {
        "defaultStat": 88888,
        "incrementByLevel": 300.05
      },
      "defCorrection": 3,
      "minSpeedList": [
        1,
        2,
        2,
        2
      ],
      "maxSpeedList": [
        3,
        3,
        4,
        4
      ],
      "uniqueAttribute": "AZURE",
      "mentalConditionInfo": {
        "add": [
          {
            "level": 1,
            "conditionIDList": [
              {
                "conditionID": "OnWinDuelAsParryingCountMultiply10AndPlus20Percent"
              },
              {
                "conditionID": "OnKillEnemyAsLevelRatioMultiply10"
              },
              {
                "conditionID": "OnKillEnemyByOtherAllyAsLevelRatioMultiply5"
              }
            ]
          }
        ],
        "min": [
          {
            "level": 1,
            "conditionIDList": [
              {
                "conditionID": "OnDieAllyAsLevelRatio10"
              }
            ]
          }
        ]
      },
      "breakSection": {
        "sectionList": [
          55,
          20
        ]
      },
      "resistInfo": {
        "atkResistList": [
          {
            "type": "SLASH",
            "value": 2
          },
          {
            "type": "PENETRATE",
            "value": 1
          },
          {
            "type": "HIT",
            "value": 0.5
          }
        ]
      },
      "attributeList": [
        {
          "skillId": 1100301,
          "number": 1
        },
        {
          "skillId": 1100302,
          "number": 1
        },
        {
          "skillId": 1100000303,
          "number": 4
        }
      ]
    },
    {
      "id": 11023,
      "appearance": "11003_Sinclair_ZweiAppearance",
      "unitKeywordList": [
        "FIXER",
        "SMALL"
      ],
      "associationList": [
        "ZWEI"
      ],
      "characterId": 10,
      "panicType": 9999,
      "season": 0,
      "defenseSkillIDList": [
        11002304
      ],
      "panicSkillOnErosion": 1000104,
      "slotWeightConditionList": [
        "Default1"
      ],
      "rank": 2,
      "hp": {
        "defaultStat": 88,
        "incrementByLevel": 3.05
      },
      "defCorrection": 3,
      "minSpeedList": [
        1,
        2,
        2,
        4
      ],
      "maxSpeedList": [
        3,
        3,
        4,
        6
      ],
      "uniqueAttribute": "INDIGO",
      "mentalConditionInfo": {
        "add": [
          {
            "level": 1,
            "conditionIDList": [
              {
                "conditionID": "OnWinDuelAsParryingCountMultiply10AndPlus20Percent"
              },
              {
                "conditionID": "OnKillEnemyAsLevelRatioMultiply10"
              },
              {
                "conditionID": "OnKillEnemyByOtherAllyAsLevelRatioMultiply5"
              }
            ]
          }
        ],
        "min": [
          {
            "level": 1,
            "conditionIDList": [
              {
                "conditionID": "OnDieAllyAsLevelRatio10"
              }
            ]
          }
        ]
      },
      "breakSection": {
        "sectionList": [
          60,
          30
        ]
      },
      "resistInfo": {
        "atkResistList": [
          {
            "type": "SLASH",
            "value": 2
          },
          {
            "type": "PENETRATE",
            "value": 1
          },
          {
            "type": "HIT",
            "value": 0.5
          }
        ]
      },
      "attributeList": [
        {
          "skillId": 11002301,
          "number": 3
        },
        {
          "skillId": 11002302,
          "number": 2
        },
        {
          "skillId": 11002303,
          "number": 1
        }
      ]
    }
  ]
}