{
    "id": 11105004,
    "textID": 11105004,
    "skillTier": 1,
    "skillData": [
        {
            "actionScript": "",
            "iconID": "1110504",
            "gaksungLevel": 1,
            "informationID": -1,
            "attributeType": "NEUTRAL",
            "atkType": "NONE",
            "defType": "GUARD",
            "skillMotion": "Default",
            "viewType": "BATTLE",
            "parryingCloseType": "NEAR",
            "canDuel": "false",
            "canChangeTarget": "true",
            "targetNum": 1,
            "defaultValue": 10,
            "abilityScriptList": [
                {
                    "scriptName": "SkillPowerAdderViaBuffDevide",
                    "buffData": {
                        "buffKeyword": "Vibration",
                        "target": "",
                        "buffOwner": "Target",
                        "stack": 1,
                        "turn": 0,
                        "activeRound": 0,
                        "value": 1.0,
                        "limit": 20
                    },
                    "conditionalData": {
                        "category": "",
                        "value": "",
                        "conditionBuffData": {
                            "buffKeyword": "",
                            "target": "",
                            "buffOwner": "",
                            "stack": 0,
                            "turn": 0,
                            "activeRound": 0,
                            "value": 0.0,
                            "limit": 0
                        },
                        "type": "",
                        "resultValue": "",
                        "resultBuffData": {
                            "buffKeyword": "",
                            "target": "",
                            "buffOwner": "",
                            "stack": 0,
                            "turn": 0,
                            "activeRound": 0,
                            "value": 0.0,
                            "limit": 0
                        }
                    }
                },
                {
                    "scriptName": "DiscardLowestSkillOnUse1",
                    "buffData": {
                        "buffKeyword": "",
                        "target": "",
                        "buffOwner": "",
                        "stack": 0,
                        "turn": 0,
                        "activeRound": 0,
                        "value": 0.0,
                        "limit": 0
                    },
                    "conditionalData": {
                        "category": "",
                        "value": "",
                        "conditionBuffData": {
                            "buffKeyword": "",
                            "target": "",
                            "buffOwner": "",
                            "stack": 0,
                            "turn": 0,
                            "activeRound": 0,
                            "value": 0.0,
                            "limit": 0
                        },
                        "type": "",
                        "resultValue": "",
                        "resultBuffData": {
                            "buffKeyword": "",
                            "target": "",
                            "buffOwner": "",
                            "stack": 0,
                            "turn": 0,
                            "activeRound": 0,
                            "value": 0.0,
                            "limit": 0
                        }
                    }
                }
            ],
            "mpUsage": 0,
            "skillLevelCorrection": 0,
            "range": -1.0,
            "arearange": -1.0,
            "skillTargetType": "FRONT",
            "canTeamKill": "false",
            "coinList": [
                {
                    "operatorType": "ADD",
                    "color": "GOLD",
                    "grade": 1,
                    "abilityScriptList": [],
                    "scale": 5,
                    "prob": 0.5,
                    "actionIndex": -1,
                    "cutsceneStart": false
                }
            ],
            "actionList": []
        },
        {
            "actionScript": "",
            "iconID": "1110504_4",
            "gaksungLevel": 4,
            "informationID": -1,
            "attributeType": "AMBER",
            "atkType": "ERROR",
            "defType": "NONE",
            "skillMotion": "Empty",
            "viewType": "NONE",
            "parryingCloseType": "NONE",
            "canDuel": "",
            "canChangeTarget": "",
            "targetNum": -1,
            "defaultValue": 12,
            "abilityScriptList": [],
            "mpUsage": -1,
            "skillLevelCorrection": 2147483647,
            "range": -1.0,
            "arearange": -1.0,
            "skillTargetType": "NONE",
            "canTeamKill": "",
            "coinList": [],
            "actionList": []
        }
    ],
    "requireIDList": [],
    "skillTagList": [],
    "skillType": "SKILL"
}